astral_mcp_server/__init__.py
astral_mcp_server/config.py
astral_mcp_server/helpers/__init__.py
astral_mcp_server/helpers/geojson.py
astral_mcp_server/helpers/utils.py
astral_mcp_server/helpers/validation.py
astral_mcp_server/server.py
astral_mcp_server-0.1.1.dist-info/entry_points.txt
astral_mcp_server-0.1.1.dist-info/LICENSE
astral_mcp_server-0.1.1.dist-info/METADATA
astral_mcp_server-0.1.1.dist-info/WHEEL
astral_mcp_server-0.1.1.dist-info/RECORD
