Metadata-Version: 2.3
Name: astral-mcp-server
Version: 0.1.1
Summary: A MCP (Model Context Protocol) server that enables AI models to query location attestations using the Astral GraphQL endpoints and APIs
Author: AR
Requires-Python: >=3.12,<4.0
Classifier: Programming Language :: Python :: 3
Classifier: Programming Language :: Python :: 3.12
Classifier: Programming Language :: Python :: 3.13
Requires-Dist: httpx (>=0.27.0,<0.28.0)
Requires-Dist: mcp[cli] (>=1.0.0,<2.0.0)
